pep695/__init__.py
pep695/__main__.py
pep695/cli.py
pep695-1.0.2.dist-info/METADATA
pep695-1.0.2.dist-info/WHEEL
pep695-1.0.2.dist-info/entry_points.txt
pep695-1.0.2.dist-info/top_level.txt
pep695-1.0.2.dist-info/RECORD
