Metadata-Version: 2.1
Name: pep695
Version: 1.0.2
Summary: pep695 is now autopep695
Classifier: Development Status :: 7 - Inactive
Requires-Dist: autopep695
